<Entry xml:id="drobina">
  <pb n="118" end_page="119" />
  <form type="reconstructed" xml:lang="ocs">
    <orth>*drobina</orth>
    <lemma>drobina</lemma>
  </form>
  <etym type="cognates">
    <item>
      <form>
        <orth xml:lang="bul" type="dialect">болг. диал. <ref>дрббини</ref> мн.</orth>
      </form>
      <sense>
        <def>выжарки, шкварки (Георгиев), дрббини мн. род мясной пищи</def>
      </sense>
      <cit type="bibl">
        <bibl>(Т. В. Швецова. Словарь говора села Твардицы 87)</bibl>
      </cit>
    </item>
    <item>
      <form>
        <orth xml:lang="srp">сербохорв. <ref>дробина</ref> ж. р.</orth>
      </form>
      <sense>
        <def>требуха, внутрен­ ности</def>
      </sense>
      <cit type="bibl">
        <bibl>(РСА IV, 726)</bibl>
      </cit>
    </item>
    <item>
      <form>
        <orth xml:lang="slv">словен. <ref>drobina</ref> ж. р.</orth>
      </form>
      <sense>
        <def>осколки камня</def>
      </sense>
      <cit type="bibl">
        <bibl>(Slovar sloven, jezika. I, 500)</bibl>
      </cit>
    </item>
    <item>
      <form>
        <orth xml:lang="ces" type="old">ст.-чеш. <ref>drobina</ref> ж. p.</orth>
      </form>
      <sense>
        <def>minutum (Ст.-чеш., Прага)</def>
      </sense>
    </item>
    <item>
      <form>
        <orth xml:lang="ces">чеш. <ref>drobina</ref> ж. р.</orth>
      </form>
      <sense>
        <def>крошка, кусочек , сюда же</def>
      </sense>
      <cit type="bibl">
        <bibl>(Jung- mann I, 481, с пометой: sic; Kott I, 311: Komensky)</bibl>
      </cit>
    </item>
    <item>
      <form>
        <orth xml:lang="ces" type="dialect">диал. <ref>drobinka</ref> ж. p.</orth>
      </form>
      <sense>
        <def>крошка (хлеба и т. и.), крошево для по­ хлебки , крошка, кусочек (хлеба и т. и.) , drobinek, род. п. -nka, м. р. то же , drobinek, род. п. -nka, м. р. то же</def>
      </sense>
      <cit type="bibl">
        <bibl>(Gregor. Slov. slavk.-bucov. 46)</bibl>
      </cit>
      <cit type="bibl">
        <bibl>(Sverak. Boskov. 108)</bibl>
      </cit>
      <cit type="bibl">
        <bibl>(Gregor. Slov. slavk.-bucov. 46)</bibl>
      </cit>
      <cit type="bibl">
        <bibl>(Sverak. Boskov. 108)</bibl>
      </cit>
    </item>
    <item>
      <form>
        <orth xml:lang="slk">слвц. <ref>drobin</ref>(k)a</orth>
      </form>
      <cit type="bibl">
        <bibl>(Kalal 116)</bibl>
      </cit>
    </item>
    <item>
      <form>
        <orth xml:lang="hsb">в.-луж. <ref>dro</ref>­ bina ж, p., собир.</orth>
      </form>
      <sense>
        <def>мелочь, дребедень</def>
      </sense>
      <cit type="bibl">
        <bibl>(Pfuhl 164)</bibl>
      </cit>
    </item>
    <item>
      <form>
        <orth xml:lang="svc">словин. <ref>dru</ref>§b- jina ж. р.</orth>
      </form>
      <sense>
        <def>мелочь, крошка</def>
      </sense>
      <cit type="bibl">
        <bibl>(Lorentz Slovinz. Wb. I, 205)</bibl>
      </cit>
    </item>
    <item>
      <form>
        <orth xml:lang="rus" type="dialect">русск. диал. <ref>дробина</ref> ж. р., собир.</orth>
      </form>
      <sense>
        <def>мелкий скот, дворовая птица южн., , дробина гуща, остающаяся в чану для приго­ товления браги , остатки от выделки пива , виноградные выжимки (донск., астрах.), (мн.) размолотый вместе с шелухой картофель (вят.), слишком пере­ варившееся мясо (арх.), о толстой, рыхлой женщине (волог.) , дробины мн. гуща, остающаяся по спуске квасу, пива; употребляется в пойло скотине</def>
      </sense>
      <cit type="bibl">
        <bibl>(Даль 3 I, 1225)</bibl>
      </cit>
      <cit type="bibl">
        <bibl>(Куликовский 20)</bibl>
      </cit>
      <cit type="bibl">
        <bibl>(Мельниченко 61)</bibl>
      </cit>
      <cit type="bibl">
        <bibl>(Филин 8, 187)</bibl>
      </cit>
      <cit type="bibl">
        <bibl>(Васнецов 61)</bibl>
      </cit>
    </item>
    <item>
      <form>
        <orth xml:lang="ukr">укр. <ref>дробина</ref> ж. р., собир.</orth>
      </form>
      <sense>
        <def>домашние птицы, мелкие пресмыкающиеся, также •drobb черви, дрова из тонких веток, мелкие вещи, мелкие деньги, мелкие куски</def>
      </sense>
      <cit type="bibl">
        <bibl>(Гринченко I, 446)</bibl>
      </cit>
    </item>
    <item>
      <form>
        <orth xml:lang="ukr" type="dialect">диал. <ref>дробынаж</ref>. р.</orth>
      </form>
      <sense>
        <def>немного . — Сюда же такие производные как</def>
      </sense>
      <cit type="bibl">
        <bibl>(Ф, Д. Климчук. Специфическая лексика Дрогичинского Полесья'. — «Лексика Полесья» 32)</bibl>
      </cit>
    </item>
    <item>
      <form>
        <orth xml:lang="bul" type="dialect">болг. диал. <ref>друбинё</ref> ср. р.</orth>
      </form>
      <sense>
        <def>требуха, внутренности, потроха, сербо­ хорв. дробйтье ср. р. то же</def>
      </sense>
      <cit type="bibl">
        <bibl>(Н. Ковачев. Севлиевско. — БД V, 18; Младенов БТР: дробине ср. р.)</bibl>
      </cit>
      <cit type="bibl">
        <bibl>(РСА IV, 726)</bibl>
      </cit>
    </item>
  </etym>
  <gramGrp>
    <gram>Производное с суфф.<m type="suffix">
        <ref>-та</ref>
      </m>, 
соотносительное с <ref type="etymon" target="drobiti">* drobiti</ref>, 
<ref type="etymon" target="drobb-2">*drobb</ref>, 
<ref type="etymon" target="drobb-2">*drobb</ref> (см.).</gram>
  </gramGrp>
</Entry>