<Entry xml:id="ecmenecmennj">
  <pb n="62" />
  <form type="reconstructed" xml:lang="ocs">
    <orth>*ęčьmenъ/*ęčьmenьnъjь</orth>
    <lemma>ęčьmenъ/*ęčьmenьnъjь</lemma>
  </form>
  <form type="reconstructed" xml:lang="ocs">
    <orth>§сыпепьпъ]ь</orth>
    <lemma>§сыпепьпъ]ь</lemma>
  </form>
  <etym type="cognates">
    <item>
      <form>
        <orth xml:lang="bul" type="dialect">болг. диал. <ref>ечмён</ref>, -а, -о, прилаг.</orth>
      </form>
      <sense>
        <def>ячмен­ ный , ичимён , ичумён</def>
      </sense>
      <cit type="bibl">
        <bibl>(РБЕ; Дювернуа: ячемян)</bibl>
      </cit>
      <cit type="bibl">
        <bibl>(М. Младенов БД III, 80)</bibl>
      </cit>
      <cit type="bibl">
        <bibl>(Д. Евстатиева. С. Тръстеник, Плевенско. — БД VI, 181)</bibl>
      </cit>
    </item>
    <item>
      <form>
        <orth xml:lang="mac">макед. ]<ref>ачмен</ref>
        </orth>
      </form>
      <sense>
        <def>ячменный</def>
      </sense>
      <cit type="bibl">
        <bibl>(И-С)</bibl>
      </cit>
    </item>
    <item>
      <form>
        <orth xml:lang="srp" type="old">сербохорв. стар. , редк. <ref>jecmeni</ref>, прилаг.</orth>
      </form>
      <sense>
        <def>ячменный , также jacmenl, прилаг. , ]ёчмен, -а, -о ячменный</def>
      </sense>
      <cit type="bibl">
        <bibl>(XVIII в., RJA IV, 507)</bibl>
      </cit>
      <cit type="bibl">
        <bibl>(RJA IV, 392)</bibl>
      </cit>
    </item>
    <item>
      <form>
        <orth xml:lang="slv">словен. ]<ref>естёп</ref>%</orth>
      </form>
    </item>
  </etym>
  <note>прилаг. то же (Plet. I, 362), также jecmenji (там же), чеш. /ес- теппу, прилаг. 'ячменный', слвц. jacmenny (SSJ I, 627), н.-луж. jacmeny 'ячменный, ячный' (Muka St. I, 521), польск. j$czmienny, прилаг. 'ячменный' (Warsz. II, 176), диал. j$czmianny, jpczmionny то же, словин. jiclemni, прилаг. 'ячменный' (Lorentz Slovinz. Wb. I, 393), др.-русск. шъменьныи 'ячменный' (Остр, ев., Срезневский III, 1675), русск. ячменный, -ая, -ое, укр. ячмтний 'ячменный' (Грин­ ченко IV, 546). Прилаг. от основы *$сътеп- (<xr type="compare">см. <ref type="etymon" target="stu-2">*$съту</ref>
    </xr>): 1) архаичного типа,, 
представляющее собой безаффиксную именную основу — *$сътепъ;: 
2) регулярное производное с суфф. -ъпъ от основы *$сътеп~.): 1) архаичного типа,, 
представляющее собой безаффиксную именную основу — *$сътепъ;: 
2) регулярное производное с суфф. -ъпъ от основы *$сътеп~.): 1) архаичного типа,, 
представляющее собой безаффиксную именную основу — *$сътепъ;: 
2) регулярное производное с суфф. -ъпъ от основы *$сътеп~.): 1) архаичного типа,, 
представляющее собой безаффиксную именную основу — *$сътепъ;: 
2) регулярное производное с суфф. -ъпъ от основы *$сътеп~.</note>
</Entry>