<Entry xml:id="glaz">
  <pb n="117" end_page="118" />
  <form type="reconstructed" xml:lang="ocs">
    <orth>*glazъ</orth>
    <lemma>glazъ</lemma>
  </form>
  <etym type="cognates">
    <item>
      <form>
        <orth xml:lang="ces" type="old">чеш. стар, <ref>hlaz</ref> м. р.</orth>
      </form>
      <sense>
        <def>глаз</def>
      </sense>
      <cit type="bibl">
        <bibl>(Kott I. 429; из русск.?)</bibl>
      </cit>
    </item>
    <item>
      <form>
        <orth xml:lang="pol">польск. <ref>glaz</ref> м. р.</orth>
      </form>
      <sense>
        <def>крупный камень, булыжник , др.-</def>
      </sense>
      <cit type="bibl">
        <bibl>(Dorosz. II, 1151)</bibl>
      </cit>
    </item>
    <item>
      <form>
        <orth xml:lang="rus">русск. <ref>глазъ</ref> сглаз</orth>
      </form>
      <sense>
        <def>, сюда же ум. глазъкъ шарик</def>
      </sense>
      <cit type="bibl">
        <bibl>(Срезневский I, 518)</bibl>
      </cit>
      <cit type="bibl">
        <bibl>(Ип. л. под 1114 г., там же; см. также СлРЯ XI— XVII вв. 4)</bibl>
      </cit>
    </item>
    <item>
      <form>
        <orth xml:lang="rus">русск. <ref>глаз</ref> м. р.</orth>
      </form>
      <sense>
        <def>орган зрения, глаз, глазок, род. п. -зка, м. р. в растущем дереве очко, почка листовая, с(о перстне и о подобной вещи) одиночный камешек, жемчужина, ячейка, ячея сети</def>
      </sense>
      <cit type="bibl">
        <bibl>(Даль 3 I, 873)</bibl>
      </cit>
    </item>
    <item>
      <form>
        <orth xml:lang="rus" type="dialect">диал. <ref>глаз</ref> м. р.</orth>
      </form>
      <sense>
        <def>ячейка сети , глаз , глазок, род. п. -зка, м. р. род кружевной вышивки (волог.), петелька, образуемая при вязании чулок, варежек и других вязаных изделий (Эст. ССР, Латв. ССР, Лит. ССР)</def>
      </sense>
      <cit type="bibl">
        <bibl>(астрах., пек., ср.-урал., Филин 6, 184)</bibl>
      </cit>
      <cit type="bibl">
        <bibl>(Деулинский словарь 110)</bibl>
      </cit>
      <cit type="bibl">
        <bibl>(Филин 6, 190)</bibl>
      </cit>
    </item>
    <item>
      <form>
        <orth xml:lang="ukr">укр. <ref>глазки</ref> мн.</orth>
      </form>
      <sense>
        <def>железные грузила у невода , возм., сюда же лазок, род. п. -зка, м. р. грузило металли­ ческое на сетях</def>
      </sense>
      <cit type="bibl">
        <bibl>(Гринченко I, 288)</bibl>
      </cit>
      <cit type="bibl">
        <bibl>(Гринченко II, 341)</bibl>
      </cit>
    </item>
    <item>
      <form>
        <orth xml:lang="bel" type="old">ст.-блр. <ref>Глаз</ref>, личное имя собств. . — Прямых ю.-слав. сви­ детельств праслав. *glazъ мы не знаем, но ср., возм., сюда же</orth>
      </form>
      <cit type="bibl">
        <bibl>(XVI—XVII вв., Б1рыла 110)</bibl>
      </cit>
    </item>
    <item>
      <form>
        <orth xml:lang="bul">болг. <ref>Глазо</ref> м. р., личное имя собств., Глазов, фам.</orth>
      </form>
      <cit type="bibl">
        <bibl>(Ст. Илчев. Речник на личните и фамилии имена у българите 135: от диал. *глаз 'большой камень')</bibl>
      </cit>
    </item>
    <item>
      <form>
        <orth xml:lang="mac">макед. %<ref>уров</ref> глас</orth>
      </form>
      <sense>
        <def>скала Джуро . Косвенные, производные ю.-слав. свидетельства см. под *glazbnb</def>
      </sense>
      <cit type="bibl">
        <bibl>(В. von Arnim. Urslav. glazъ auch im Siidslavischen. — ZfslPh XIV, 1937, 104)</bibl>
      </cit>
    </item>
  </etym>
  <note>Скорее всего, членится как *gl-a-zъ, суффиксальное производ­ ное от и.-е. *g(h)el- 'круглое, шарообразное, камешек'. Литера­ тура о слав, *glazъ, кроме того, насчитывает целый ряд спорных теорий и гипотез. Ср., напр., так наз. закон Цупицы о переходе слав, z &lt;^ s, согласно кот. слав. *glazb сближалось со ср.-нж.- нем. glaren 'блестеть, гореть, пылать', англ. to glare 'сиять', др.-в.-нем. glas 'стекло'. См. Е. Zupitza. Miszellen. 2. Zur Her- kunft des urslavischen z.—KZ X X X V I I , 1904, 398; G. Iljinskij RS 6, 1913, 215—219; Berneker I, 301. Совершенной неудачей оказался затем «закон Иокля», предполагавший деназализацию и родство русск. глаз и ст.-слав. ГЛАДДТИ, ГЛАДДТИ 'videre', русск. глядеть, причем глаз — якобы из *gl?d-z-. См. N. Jokl. Ein urslavisches Entnasalierungsgesetz. — AfslPh X X V I I I , 1906, 1—2; против см. J. Charpentier AfslPh X X I X , 1907, 5; см. еще N. Jokl AfslPh X X I X , 1907, 1 4 - 1 5 ; A. Bruckner IF X X I I I , 206 и сл. Заслуживает внимания в связи со сказанным выше сбли­ жение слав, *glazъ с русск.-цслав. глезнъ 'лодыжка', др.-исл. klakkr 'ком' (*glogno-) 'ком', см. P. Persson. Beitrage zur idg. glazbnb(jb) Wortforschung 2, 792; Фасмер I, 409—-410 (там же дополнения); Stawski I, 288—289. См. еще М. Rudnicki. О wyrazie glaz 'bursz- tyn'. — SO 28/29, 1971, 221—224 (связывает лат. glaesum, gle- sum T]Xexxpov с праслав. *glezb и польск. glaz cсмесь серебра с зо­ лотом').</note>
</Entry>