<Entry xml:id="glipati">
  <pb n="127" end_page="128" />
  <form type="reconstructed" xml:lang="ocs">
    <orth>*glipati</orth>
    <lemma>glipati</lemma>
  </form>
  <etym type="cognates">
    <item>
      <form>
        <orth xml:lang="rus">русск. стар, <ref>глипатъ</ref>
        </orth>
      </form>
      <sense>
        <def>поглядывать куда-либо, оглядываться</def>
      </sense>
      <cit type="bibl">
        <bibl>(Даль 3 I, 876, без указания места)</bibl>
      </cit>
    </item>
    <item>
      <form>
        <orth xml:lang="ukr" type="old">ст.-укр. <ref>глипати</ref>
        </orth>
      </form>
      <sense>
        <def>оборачи­ ваясь осматривать</def>
      </sense>
      <cit type="bibl">
        <bibl>(Срезневский I, 520: Вер.)</bibl>
      </cit>
    </item>
    <item>
      <form>
        <orth xml:lang="ukr">укр. <ref>глипати</ref>
        </orth>
      </form>
      <sense>
        <def>глядеть, таращить глаза , также</def>
      </sense>
      <cit type="bibl">
        <bibl>(Гринченко I, 289)</bibl>
      </cit>
    </item>
    <item>
      <form>
        <orth xml:lang="ukr" type="dialect">диал. <ref>глипати</ref> . — Ср. сюда же — с другим исходом основы —</orth>
      </form>
      <cit type="bibl">
        <bibl>(Онишкевич. Словник бойювського д1алекту)</bibl>
      </cit>
    </item>
    <item>
      <form>
        <orth xml:lang="ukr">укр. <ref>глйтти</ref>
        </orth>
      </form>
      <sense>
        <def>глядеть, та­ ращить глаза</def>
      </sense>
      <cit type="bibl">
        <bibl>(Желех. Вх. Зн. 10, см. Гринченко I, 289)</bibl>
      </cit>
    </item>
  </etym>
  <note>Это слово ограниченного распространения объясняют как продолжение и.-е. *ghlip- I *ghlib-, откуда также ср.-в.-нем. glifen 'быть косым', glipfen 'скользить', ср.-н.-нем. glepe, glippe 'трещина, щель', норв. glipa 'быть открытым'. См. Фасмер I, 413; Rudnyckyj I, 646.</note>
  <gramGrp>
    <gram>Не исключена, однако, мысль, что перед нами экспрессивное образование и — как таковое — слав.<ref type="etymon" target="gli-">*gli-</ref>
pati можно было бы сравнить с дат. glippe 'мигать, глядеть', шв. 
glippa 'часто открывать'.</gram>
  </gramGrp>
  <note>Внешний рисунок *glipati напоминает<xr type="compare">см. <ref type="etymon" target="blimati">*blimati</ref>
    </xr>, кстати, семантически 
близкое. Нет надобности 
считать *glipati 
заимств. из греч. ^Хе-лсо 'смотреть', как 
думал 
Фасмер ранее, или из герм., как предполагал Уленбек, см. ниже. 
См. A. Fick ВВ II, 1878, 208; С. С. Uhlenbeck AfslPh X V , 1893, 
486; Berneker I, 304; A. Bruckner KZ XLVIII, 1918, 193. 
Сближение слав, слова с лит. gllbti 'слепнуть, становиться 
подслеповатым', zllbti то же см. В. Н. Чекман «Балто-славянские 
исследования» (М., 1974) 125. Предположение автора о заимство­
вании из балт. не кажется убедительным., кстати, семантически 
близкое. Нет надобности 
считать *glipati 
заимств. из греч. ^Хе-лсо 'смотреть', как 
думал 
Фасмер ранее, или из герм., как предполагал Уленбек, см. ниже. 
См. A. Fick ВВ II, 1878, 208; С. С. Uhlenbeck AfslPh X V , 1893, 
486; Berneker I, 304; A. Bruckner KZ XLVIII, 1918, 193. 
Сближение слав, слова с лит. gllbti 'слепнуть, становиться 
подслеповатым', zllbti то же см. В. Н. Чекман «Балто-славянские 
исследования» (М., 1974) 125. Предположение автора о заимство­
вании из балт. не кажется убедительным., кстати, семантически 
близкое. Нет надобности 
считать *glipati 
заимств. из греч. ^Хе-лсо 'смотреть', как 
думал 
Фасмер ранее, или из герм., как предполагал Уленбек, см. ниже. 
См. A. Fick ВВ II, 1878, 208; С. С. Uhlenbeck AfslPh X V , 1893, 
486; Berneker I, 304; A. Bruckner KZ XLVIII, 1918, 193. 
Сближение слав, слова с лит. gllbti 'слепнуть, становиться 
подслеповатым', zllbti то же см. В. Н. Чекман «Балто-славянские 
исследования» (М., 1974) 125. Предположение автора о заимство­
вании из балт. не кажется убедительным., кстати, семантически 
близкое. Нет надобности 
считать *glipati 
заимств. из греч. ^Хе-лсо 'смотреть', как 
думал 
Фасмер ранее, или из герм., как предполагал Уленбек, см. ниже. 
См. A. Fick ВВ II, 1878, 208; С. С. Uhlenbeck AfslPh X V , 1893, 
486; Berneker I, 304; A. Bruckner KZ XLVIII, 1918, 193. 
Сближение слав, слова с лит. gllbti 'слепнуть, становиться 
подслеповатым', zllbti то же см. В. Н. Чекман «Балто-славянские 
исследования» (М., 1974) 125. Предположение автора о заимство­
вании из балт. не кажется убедительным.</note>
</Entry>